[{"chapter_name": "Chapter 10", "image_links": ["//i333.ntcdntempv3.com/data/images/2871/857321/001.jpg?data=net", "//i333.ntcdntempv3.com/data/images/2871/857321/002.jpg?data=net", "//i333.ntcdntempv3.com/data/images/2871/857321/003.jpg?data=net", "//i333.ntcdntempv3.com/data/images/2871/857321/004.jpg?data=net", "//i333.ntcdntempv3.com/data/images/2871/857321/005.jpg?data=net", "//i333.ntcdntempv3.com/data/images/2871/857321/006.jpg?data=net", "//i333.ntcdntempv3.com/data/images/2871/857321/007.jpg?data=net", "//i333.ntcdntempv3.com/data/images/2871/857321/008.jpg?data=net", "//i333.ntcdntempv3.com/data/images/2871/857321/009.jpg?data=net", "//i333.ntcdntempv3.com/data/images/2871/857321/010.jpg?data=net", "//i333.ntcdntempv3.com/data/images/2871/857321/011.jpg?data=net", "//i333.ntcdntempv3.com/data/images/2871/857321/012.jpg?data=net", "//i333.ntcdntempv3.com/data/images/2871/857321/013.jpg?data=net", "//i333.ntcdntempv3.com/data/images/2871/857321/014.jpg?data=net", "//i333.ntcdntempv3.com/data/images/2871/857321/015.jpg?data=net", "//i333.ntcdntempv3.com/data/images/2871/857321/016.jpg?data=net", "//i333.ntcdntempv3.com/data/images/2871/857321/017.jpg?data=net", "//i333.ntcdntempv3.com/data/images/2871/857321/018.jpg?data=net", "//i333.ntcdntempv3.com/data/images/2871/857321/019.jpg?data=net", "//i333.ntcdntempv3.com/data/images/2871/857321/020.jpg?data=net", "//i333.ntcdntempv3.com/data/images/2871/857321/021.jpg?data=net", "//i333.ntcdntempv3.com/data/images/2871/857321/022.jpg?data=net", "//i333.ntcdntempv3.com/data/images/2871/857321/023.jpg?data=net", "//i333.ntcdntempv3.com/data/images/2871/857321/024.jpg?data=net"]}, {"chapter_name": "Chapter 9", "image_links": ["//i333.ntcdntempv3.com/data/images/2871/857320/001.jpg?data=net", "//i333.ntcdntempv3.com/data/images/2871/857320/002.jpg?data=net", "//i333.ntcdntempv3.com/data/images/2871/857320/003.jpg?data=net", "//i333.ntcdntempv3.com/data/images/2871/857320/004.jpg?data=net", "//i333.ntcdntempv3.com/data/images/2871/857320/005.jpg?data=net", "//i333.ntcdntempv3.com/data/images/2871/857320/006.jpg?data=net", "//i333.ntcdntempv3.com/data/images/2871/857320/007.jpg?data=net", "//i333.ntcdntempv3.com/data/images/2871/857320/008.jpg?data=net", "//i333.ntcdntempv3.com/data/images/2871/857320/009.jpg?data=net", "//i333.ntcdntempv3.com/data/images/2871/857320/010.jpg?data=net", "//i333.ntcdntempv3.com/data/images/2871/857320/011.jpg?data=net", "//i333.ntcdntempv3.com/data/images/2871/857320/012.jpg?data=net", "//i333.ntcdntempv3.com/data/images/2871/857320/013.jpg?data=net", "//i333.ntcdntempv3.com/data/images/2871/857320/014.jpg?data=net", "//i333.ntcdntempv3.com/data/images/2871/857320/015.jpg?data=net", "//i333.ntcdntempv3.com/data/images/2871/857320/016.jpg?data=net", "//i333.ntcdntempv3.com/data/images/2871/857320/017.jpg?data=net", "//i333.ntcdntempv3.com/data/images/2871/857320/018.jpg?data=net", "//i333.ntcdntempv3.com/data/images/2871/857320/019.jpg?data=net", "//i333.ntcdntempv3.com/data/images/2871/857320/020.jpg?data=net", "//i333.ntcdntempv3.com/data/images/2871/857320/021.jpg?data=net", "//i333.ntcdntempv3.com/data/images/2871/857320/022.jpg?data=net", "//i333.ntcdntempv3.com/data/images/2871/857320/023.jpg?data=net", "//i333.ntcdntempv3.com/data/images/2871/857320/024.jpg?data=net", "//i333.ntcdntempv3.com/data/images/2871/857320/025.jpg?data=net", "//i333.ntcdntempv3.com/data/images/2871/857320/026.jpg?data=net", "//i333.ntcdntempv3.com/data/images/2871/857320/027.jpg?data=net", "//i333.ntcdntempv3.com/data/images/2871/857320/028.jpg?data=net", "//i333.ntcdntempv3.com/data/images/2871/857320/029.jpg?data=net"]}, {"chapter_name": "Chapter 8", "image_links": ["//i333.ntcdntempv3.com/data/images/2871/857319/001.jpg?data=net", "//i333.ntcdntempv3.com/data/images/2871/857319/002.jpg?data=net", "//i333.ntcdntempv3.com/data/images/2871/857319/003.jpg?data=net", "//i333.ntcdntempv3.com/data/images/2871/857319/004.jpg?data=net", "//i333.ntcdntempv3.com/data/images/2871/857319/005.jpg?data=net", "//i333.ntcdntempv3.com/data/images/2871/857319/006.jpg?data=net", "//i333.ntcdntempv3.com/data/images/2871/857319/007.jpg?data=net", "//i333.ntcdntempv3.com/data/images/2871/857319/008.jpg?data=net", "//i333.ntcdntempv3.com/data/images/2871/857319/009.jpg?data=net", "//i333.ntcdntempv3.com/data/images/2871/857319/010.jpg?data=net", "//i333.ntcdntempv3.com/data/images/2871/857319/011.jpg?data=net", "//i333.ntcdntempv3.com/data/images/2871/857319/012.jpg?data=net", "//i333.ntcdntempv3.com/data/images/2871/857319/013.jpg?data=net", "//i333.ntcdntempv3.com/data/images/2871/857319/014.jpg?data=net", "//i333.ntcdntempv3.com/data/images/2871/857319/015.jpg?data=net", "//i333.ntcdntempv3.com/data/images/2871/857319/016.jpg?data=net", "//i333.ntcdntempv3.com/data/images/2871/857319/017.jpg?data=net", "//i333.ntcdntempv3.com/data/images/2871/857319/018.jpg?data=net", "//i333.ntcdntempv3.com/data/images/2871/857319/019.jpg?data=net", "//i333.ntcdntempv3.com/data/images/2871/857319/020.jpg?data=net", "//i333.ntcdntempv3.com/data/images/2871/857319/021.jpg?data=net", "//i333.ntcdntempv3.com/data/images/2871/857319/022.jpg?data=net", "//i333.ntcdntempv3.com/data/images/2871/857319/023.jpg?data=net", "//i333.ntcdntempv3.com/data/images/2871/857319/024.jpg?data=net", "//i333.ntcdntempv3.com/data/images/2871/857319/025.jpg?data=net", "//i333.ntcdntempv3.com/data/images/2871/857319/026.jpg?data=net", "//i333.ntcdntempv3.com/data/images/2871/857319/027.jpg?data=net", "//i333.ntcdntempv3.com/data/images/2871/857319/028.jpg?data=net", "//i333.ntcdntempv3.com/data/images/2871/857319/029.jpg?data=net"]}, {"chapter_name": "Chapter 7", "image_links": ["//i333.ntcdntempv3.com/data/images/2871/857318/001.jpg?data=net", "//i333.ntcdntempv3.com/data/images/2871/857318/002.jpg?data=net", "//i333.ntcdntempv3.com/data/images/2871/857318/003.jpg?data=net", "//i333.ntcdntempv3.com/data/images/2871/857318/004.jpg?data=net", "//i333.ntcdntempv3.com/data/images/2871/857318/005.jpg?data=net", "//i333.ntcdntempv3.com/data/images/2871/857318/006.jpg?data=net", "//i333.ntcdntempv3.com/data/images/2871/857318/007.jpg?data=net", "//i333.ntcdntempv3.com/data/images/2871/857318/008.jpg?data=net", "//i333.ntcdntempv3.com/data/images/2871/857318/009.jpg?data=net", "//i333.ntcdntempv3.com/data/images/2871/857318/010.jpg?data=net", "//i333.ntcdntempv3.com/data/images/2871/857318/011.jpg?data=net", "//i333.ntcdntempv3.com/data/images/2871/857318/012.jpg?data=net", "//i333.ntcdntempv3.com/data/images/2871/857318/013.jpg?data=net", "//i333.ntcdntempv3.com/data/images/2871/857318/014.jpg?data=net", "//i333.ntcdntempv3.com/data/images/2871/857318/015.jpg?data=net", "//i333.ntcdntempv3.com/data/images/2871/857318/016.jpg?data=net", "//i333.ntcdntempv3.com/data/images/2871/857318/017.jpg?data=net", "//i333.ntcdntempv3.com/data/images/2871/857318/018.jpg?data=net", "//i333.ntcdntempv3.com/data/images/2871/857318/019.jpg?data=net", "//i333.ntcdntempv3.com/data/images/2871/857318/020.jpg?data=net", "//i333.ntcdntempv3.com/data/images/2871/857318/021.jpg?data=net", "//i333.ntcdntempv3.com/data/images/2871/857318/022.jpg?data=net", "//i333.ntcdntempv3.com/data/images/2871/857318/023.jpg?data=net", "//i333.ntcdntempv3.com/data/images/2871/857318/024.jpg?data=net", "//i333.ntcdntempv3.com/data/images/2871/857318/025.jpg?data=net", "//i333.ntcdntempv3.com/data/images/2871/857318/026.jpg?data=net", "//i333.ntcdntempv3.com/data/images/2871/857318/027.jpg?data=net"]}, {"chapter_name": "Chapter 6", "image_links": ["//i333.ntcdntempv3.com/data/images/2871/857317/001.jpg?data=net", "//i333.ntcdntempv3.com/data/images/2871/857317/002.jpg?data=net", "//i333.ntcdntempv3.com/data/images/2871/857317/003.jpg?data=net", "//i333.ntcdntempv3.com/data/images/2871/857317/004.jpg?data=net", "//i333.ntcdntempv3.com/data/images/2871/857317/005.jpg?data=net", "//i333.ntcdntempv3.com/data/images/2871/857317/006.jpg?data=net", "//i333.ntcdntempv3.com/data/images/2871/857317/007.jpg?data=net", "//i333.ntcdntempv3.com/data/images/2871/857317/008.jpg?data=net", "//i333.ntcdntempv3.com/data/images/2871/857317/009.jpg?data=net", "//i333.ntcdntempv3.com/data/images/2871/857317/010.jpg?data=net", "//i333.ntcdntempv3.com/data/images/2871/857317/011.jpg?data=net", "//i333.ntcdntempv3.com/data/images/2871/857317/012.jpg?data=net", "//i333.ntcdntempv3.com/data/images/2871/857317/013.jpg?data=net", "//i333.ntcdntempv3.com/data/images/2871/857317/014.jpg?data=net", "//i333.ntcdntempv3.com/data/images/2871/857317/015.jpg?data=net", "//i333.ntcdntempv3.com/data/images/2871/857317/016.jpg?data=net", "//i333.ntcdntempv3.com/data/images/2871/857317/017.jpg?data=net", "//i333.ntcdntempv3.com/data/images/2871/857317/018.jpg?data=net", "//i333.ntcdntempv3.com/data/images/2871/857317/019.jpg?data=net", "//i333.ntcdntempv3.com/data/images/2871/857317/020.jpg?data=net", "//i333.ntcdntempv3.com/data/images/2871/857317/021.jpg?data=net", "//i333.ntcdntempv3.com/data/images/2871/857317/022.jpg?data=net", "//i333.ntcdntempv3.com/data/images/2871/857317/023.jpg?data=net", "//i333.ntcdntempv3.com/data/images/2871/857317/024.jpg?data=net", "//i333.ntcdntempv3.com/data/images/2871/857317/025.jpg?data=net", "//i333.ntcdntempv3.com/data/images/2871/857317/026.jpg?data=net", "//i333.ntcdntempv3.com/data/images/2871/857317/027.jpg?data=net", "//i333.ntcdntempv3.com/data/images/2871/857317/028.jpg?data=net", "//i333.ntcdntempv3.com/data/images/2871/857317/029.jpg?data=net", "//i333.ntcdntempv3.com/data/images/2871/857317/030.jpg?data=net", "//i333.ntcdntempv3.com/data/images/2871/857317/031.jpg?data=net", "//i333.ntcdntempv3.com/data/images/2871/857317/032.jpg?data=net", "//i333.ntcdntempv3.com/data/images/2871/857317/033.jpg?data=net", "//i333.ntcdntempv3.com/data/images/2871/857317/034.jpg?data=net"]}, {"chapter_name": "Chapter 5", "image_links": ["//i333.ntcdntempv3.com/data/images/2871/857316/001.jpg?data=net", "//i333.ntcdntempv3.com/data/images/2871/857316/002.jpg?data=net", "//i333.ntcdntempv3.com/data/images/2871/857316/003.jpg?data=net", "//i333.ntcdntempv3.com/data/images/2871/857316/004.jpg?data=net", "//i333.ntcdntempv3.com/data/images/2871/857316/005.jpg?data=net", "//i333.ntcdntempv3.com/data/images/2871/857316/006.jpg?data=net", "//i333.ntcdntempv3.com/data/images/2871/857316/007.jpg?data=net", "//i333.ntcdntempv3.com/data/images/2871/857316/008.jpg?data=net", "//i333.ntcdntempv3.com/data/images/2871/857316/009.jpg?data=net", "//i333.ntcdntempv3.com/data/images/2871/857316/010.jpg?data=net", "//i333.ntcdntempv3.com/data/images/2871/857316/011.jpg?data=net", "//i333.ntcdntempv3.com/data/images/2871/857316/012.jpg?data=net", "//i333.ntcdntempv3.com/data/images/2871/857316/013.jpg?data=net", "//i333.ntcdntempv3.com/data/images/2871/857316/014.jpg?data=net", "//i333.ntcdntempv3.com/data/images/2871/857316/015.jpg?data=net", "//i333.ntcdntempv3.com/data/images/2871/857316/016.jpg?data=net", "//i333.ntcdntempv3.com/data/images/2871/857316/017.jpg?data=net", "//i333.ntcdntempv3.com/data/images/2871/857316/018.jpg?data=net", "//i333.ntcdntempv3.com/data/images/2871/857316/019.jpg?data=net", "//i333.ntcdntempv3.com/data/images/2871/857316/020.jpg?data=net", "//i333.ntcdntempv3.com/data/images/2871/857316/021.jpg?data=net", "//i333.ntcdntempv3.com/data/images/2871/857316/022.jpg?data=net", "//i333.ntcdntempv3.com/data/images/2871/857316/023.jpg?data=net", "//i333.ntcdntempv3.com/data/images/2871/857316/024.jpg?data=net", "//i333.ntcdntempv3.com/data/images/2871/857316/025.jpg?data=net"]}, {"chapter_name": "Chapter 4", "image_links": ["//i111.ntcdntempv3.com/data/images/2871/34599/001-fix.jpg?data=net", "//i111.ntcdntempv3.com/data/images/2871/34599/002-fix.jpg?data=net", "//i111.ntcdntempv3.com/data/images/2871/34599/003-fix.jpg?data=net", "//i111.ntcdntempv3.com/data/images/2871/34599/004-fix.jpg?data=net", "//i111.ntcdntempv3.com/data/images/2871/34599/005-fix.jpg?data=net", "//i111.ntcdntempv3.com/data/images/2871/34599/006-fix.jpg?data=net", "//i111.ntcdntempv3.com/data/images/2871/34599/007-fix.jpg?data=net", "//i111.ntcdntempv3.com/data/images/2871/34599/008-fix.jpg?data=net", "//i111.ntcdntempv3.com/data/images/2871/34599/009-fix.jpg?data=net", "//i111.ntcdntempv3.com/data/images/2871/34599/010-fix.jpg?data=net", "//i111.ntcdntempv3.com/data/images/2871/34599/011-fix.jpg?data=net", "//i111.ntcdntempv3.com/data/images/2871/34599/012-fix.jpg?data=net", "//i111.ntcdntempv3.com/data/images/2871/34599/013-fix.jpg?data=net", "//i111.ntcdntempv3.com/data/images/2871/34599/014-fix.jpg?data=net", "//i111.ntcdntempv3.com/data/images/2871/34599/015-fix.jpg?data=net", "//i111.ntcdntempv3.com/data/images/2871/34599/016-fix.jpg?data=net", "//i111.ntcdntempv3.com/data/images/2871/34599/017-fix.jpg?data=net", "//i111.ntcdntempv3.com/data/images/2871/34599/018-fix.jpg?data=net", "//i111.ntcdntempv3.com/data/images/2871/34599/019-fix.jpg?data=net", "//i111.ntcdntempv3.com/data/images/2871/34599/020-fix.jpg?data=net", "//i111.ntcdntempv3.com/data/images/2871/34599/021-fix.jpg?data=net", "//i111.ntcdntempv3.com/data/images/2871/34599/022-fix.jpg?data=net", "//i111.ntcdntempv3.com/data/images/2871/34599/023-fix.jpg?data=net", "//i111.ntcdntempv3.com/data/images/2871/34599/024-fix.jpg?data=net"]}, {"chapter_name": "Chapter 3", "image_links": ["//i111.ntcdntempv3.com/data/images/2871/34597/001-fix.jpg?data=net", "//i111.ntcdntempv3.com/data/images/2871/34597/002-fix.jpg?data=net", "//i111.ntcdntempv3.com/data/images/2871/34597/003-fix.jpg?data=net", "//i111.ntcdntempv3.com/data/images/2871/34597/004-fix.jpg?data=net", "//i111.ntcdntempv3.com/data/images/2871/34597/005-fix.jpg?data=net", "//i111.ntcdntempv3.com/data/images/2871/34597/006-fix.jpg?data=net", "//i111.ntcdntempv3.com/data/images/2871/34597/007-fix.jpg?data=net", "//i111.ntcdntempv3.com/data/images/2871/34597/008-fix.jpg?data=net", "//i111.ntcdntempv3.com/data/images/2871/34597/009-fix.jpg?data=net", "//i111.ntcdntempv3.com/data/images/2871/34597/010-fix.jpg?data=net", "//i111.ntcdntempv3.com/data/images/2871/34597/011-fix.jpg?data=net", "//i111.ntcdntempv3.com/data/images/2871/34597/012-fix.jpg?data=net", "//i111.ntcdntempv3.com/data/images/2871/34597/013-fix.jpg?data=net", "//i111.ntcdntempv3.com/data/images/2871/34597/014-fix.jpg?data=net", "//i111.ntcdntempv3.com/data/images/2871/34597/015-fix.jpg?data=net", "//i111.ntcdntempv3.com/data/images/2871/34597/016-fix.jpg?data=net", "//i111.ntcdntempv3.com/data/images/2871/34597/017-fix.jpg?data=net", "//i111.ntcdntempv3.com/data/images/2871/34597/018-fix.jpg?data=net", "//i111.ntcdntempv3.com/data/images/2871/34597/019-fix.jpg?data=net", "//i111.ntcdntempv3.com/data/images/2871/34597/020-fix.jpg?data=net", "//i111.ntcdntempv3.com/data/images/2871/34597/021-fix.jpg?data=net", "//i111.ntcdntempv3.com/data/images/2871/34597/022-fix.jpg?data=net", "//i111.ntcdntempv3.com/data/images/2871/34597/023-fix.jpg?data=net", "//i111.ntcdntempv3.com/data/images/2871/34597/024-fix.jpg?data=net", "//i111.ntcdntempv3.com/data/images/2871/34597/025-fix.jpg?data=net"]}, {"chapter_name": "Chapter 2", "image_links": ["//i111.ntcdntempv3.com/data/images/2871/34595/001.jpg?data=net", "//i111.ntcdntempv3.com/data/images/2871/34595/002.jpg?data=net", "//i111.ntcdntempv3.com/data/images/2871/34595/003.jpg?data=net", "//i111.ntcdntempv3.com/data/images/2871/34595/004.jpg?data=net", "//i111.ntcdntempv3.com/data/images/2871/34595/005.jpg?data=net", "//i111.ntcdntempv3.com/data/images/2871/34595/006.jpg?data=net", "//i111.ntcdntempv3.com/data/images/2871/34595/007.jpg?data=net", "//i111.ntcdntempv3.com/data/images/2871/34595/008.jpg?data=net", "//i111.ntcdntempv3.com/data/images/2871/34595/009.jpg?data=net", "//i111.ntcdntempv3.com/data/images/2871/34595/010.jpg?data=net", "//i111.ntcdntempv3.com/data/images/2871/34595/011.jpg?data=net", "//i111.ntcdntempv3.com/data/images/2871/34595/012.jpg?data=net", "//i111.ntcdntempv3.com/data/images/2871/34595/013.jpg?data=net", "//i111.ntcdntempv3.com/data/images/2871/34595/014.jpg?data=net", "//i111.ntcdntempv3.com/data/images/2871/34595/015.jpg?data=net", "//i111.ntcdntempv3.com/data/images/2871/34595/016.jpg?data=net", "//i111.ntcdntempv3.com/data/images/2871/34595/017.jpg?data=net", "//i111.ntcdntempv3.com/data/images/2871/34595/018.jpg?data=net", "//i111.ntcdntempv3.com/data/images/2871/34595/019.jpg?data=net", "//i111.ntcdntempv3.com/data/images/2871/34595/020.jpg?data=net", "//i111.ntcdntempv3.com/data/images/2871/34595/021.jpg?data=net", "//i111.ntcdntempv3.com/data/images/2871/34595/022.jpg?data=net", "//i111.ntcdntempv3.com/data/images/2871/34595/023.jpg?data=net", "//i111.ntcdntempv3.com/data/images/2871/34595/024.jpg?data=net", "//i111.ntcdntempv3.com/data/images/2871/34595/025.jpg?data=net", "//i111.ntcdntempv3.com/data/images/2871/34595/026.jpg?data=net", "//i111.ntcdntempv3.com/data/images/2871/34595/027.jpg?data=net"]}, {"chapter_name": "Chapter 1", "image_links": ["//i8.ntcdntempv3.com/data/images/2871/34593/001-fix.jpg?data=net", "//i8.ntcdntempv3.com/data/images/2871/34593/002-fix.jpg?data=net", "//i8.ntcdntempv3.com/data/images/2871/34593/003-fix.jpg?data=net", "//i8.ntcdntempv3.com/data/images/2871/34593/004-fix.jpg?data=net", "//i8.ntcdntempv3.com/data/images/2871/34593/005-fix.jpg?data=net", "//i8.ntcdntempv3.com/data/images/2871/34593/006-fix.jpg?data=net", "//i8.ntcdntempv3.com/data/images/2871/34593/007-fix.jpg?data=net", "//i8.ntcdntempv3.com/data/images/2871/34593/008-fix.jpg?data=net", "//i8.ntcdntempv3.com/data/images/2871/34593/009-fix.jpg?data=net", "//i8.ntcdntempv3.com/data/images/2871/34593/010-fix.jpg?data=net", "//i8.ntcdntempv3.com/data/images/2871/34593/011-fix.jpg?data=net", "//i8.ntcdntempv3.com/data/images/2871/34593/012-fix.jpg?data=net", "//i8.ntcdntempv3.com/data/images/2871/34593/013-fix.jpg?data=net", "//i8.ntcdntempv3.com/data/images/2871/34593/014-fix.jpg?data=net", "//i8.ntcdntempv3.com/data/images/2871/34593/015-fix.jpg?data=net", "//i8.ntcdntempv3.com/data/images/2871/34593/016-fix.jpg?data=net", "//i8.ntcdntempv3.com/data/images/2871/34593/017-fix.jpg?data=net", "//i8.ntcdntempv3.com/data/images/2871/34593/018-fix.jpg?data=net", "//i8.ntcdntempv3.com/data/images/2871/34593/019-fix.jpg?data=net", "//i8.ntcdntempv3.com/data/images/2871/34593/020-fix.jpg?data=net", "//i8.ntcdntempv3.com/data/images/2871/34593/021-fix.jpg?data=net", "//i8.ntcdntempv3.com/data/images/2871/34593/022-fix.jpg?data=net", "//i8.ntcdntempv3.com/data/images/2871/34593/023-fix.jpg?data=net", "//i8.ntcdntempv3.com/data/images/2871/34593/024-fix.jpg?data=net"]}]